{"_path":"/_blog","_dir":"","_draft":false,"_partial":true,"_locale":"","title":"Blog: »Du musst sie akzeptieren!«","description":"Eine Dokumentation über die Soziale Arbeit mit Neonazis","navigation":false,"hero":{"headline":"Blog","title":"»Du musst sie akzeptieren!«","description":"Eine Dokumentation über die Soziale Arbeit mit Neonazi"},"links":[{"label":"Einführung","to":"/#intro","icon":"i-heroicons-information-circle"},{"label":"Karte","to":"/map","icon":"i-heroicons-map-20-solid"}],"_id":"content:_blog.yml","_type":"yaml","_source":"content","_file":"_blog.yml","_extension":"yml"}