{"id":"c9c8ff10-9473-4997-99b0-bd475b82bbb2","timestamp":1737932093335,"matcher":{"static":{"/api/search.json":{"prerender":true},"/rss.xml":{"prerender":true}},"wildcard":{},"dynamic":{}},"prerendered":["/convert","/blog","/map","/","/blog/2024-01-04-test","/blog/2024-02-09-test","/map/bw-ravensburg-jugendhaus","/map/by-schwabach-jugendzentrum","/map/b-lichtenberg-judith-auer","/map/mv-neustrelitz-szenetreff-kiefernheide","/map/mv-rostock-max","/map/nds-bothel-wildfang","/blog/2024-01-01-test","/map/sl-saarlouis-projekt","/map/sn-grossenhain-jugendclub-impuls","/map/th-bad-berka-familienzentrum"]}